mml/__init__.py
mml/aggregation.py
mml/baseml.py
mml/calc_lines.py
mml/categorical_encoder.py
mml/classes.py
mml/dump.py
mml/ensemble.py
mml/gbm.py
mml/gradient.py
mml/linear.py
mml/lm.py
mml/matrix.py
mml/metrices.py
mml/metrics.py
mml/ml.py
mml/nn.py
mml/nn_activation.py
mml/nn_auto_nn_frame.py
mml/nn_base.py
mml/nn_layer_dense.py
mml/nn_layer_dropout.py
mml/nn_layer_flatten.py
mml/nn_layer_lstm.py
mml/nn_layer_rnn.py
mml/nn_layers.py
mml/nn_loss.py
mml/nn_module.py
mml/nn_optimizer.py
mml/nn_parameter.py
mml/nn_scheduler.py
mml/nn_sinterf_autonet.py
mml/nn_sinterf_autoneuralnet.py
mml/nn_sinterf_evaluator.py
mml/objtyp.py
mml/optimizer.py
mml/pca.py
mml/random_forest.py
mml/scaling.py
mml/setup.py
mml/simple_nn.py
mml/svm.py
mml/tensor.py
mml/threadpool.py
mml/time_series.py
mml/tree.py
mml/tree_wrapper.py
mml/wrangling.py
mml_pypi-0.0.5.dist-info/licenses/LICENSE
mml_pypi-0.0.5.dist-info/METADATA
mml_pypi-0.0.5.dist-info/WHEEL
mml_pypi-0.0.5.dist-info/top_level.txt
mml_pypi-0.0.5.dist-info/RECORD
