Metadata-Version: 2.4
Name: mml-pypi
Version: 0.0.5
Summary: My Machine Learning (MML) Library, a high performance machine learning and deep learning framework coding from scratch (pure Python) with hybrid backend support (`numpy` or `torch`).. Write `import mml` to use it.
Home-page: https://github.com/dof-studio/MML/
Author: DOF Studio
Author-email: dof.hbx@gmail.com
Classifier: Programming Language :: Python :: 3
Classifier: License :: OSI Approved :: Apache Software License
Classifier: Operating System :: OS Independent
Requires-Python: >=3.9
License-File: LICENSE
Requires-Dist: numpy
Requires-Dist: scipy
Requires-Dist: torch
Requires-Dist: pandas
Requires-Dist: matplotlib
Dynamic: author
Dynamic: author-email
Dynamic: classifier
Dynamic: description
Dynamic: description-content-type
Dynamic: home-page
Dynamic: license-file
Dynamic: requires-dist
Dynamic: requires-python
Dynamic: summary
